examples/lollipop_example.yaml
planck_2020_lollipop/__init__.py
planck_2020_lollipop/_lollipop.bibtex
planck_2020_lollipop/_lollipop.yaml
planck_2020_lollipop/_version.py
planck_2020_lollipop/bins.py
planck_2020_lollipop/lollipop.py
planck_2020_lollipop/lowlB.bibtex
planck_2020_lollipop/lowlB.yaml
planck_2020_lollipop/lowlE.bibtex
planck_2020_lollipop/lowlE.yaml
planck_2020_lollipop/lowlEB.bibtex
planck_2020_lollipop/lowlEB.yaml
planck_2020_lollipop/tools.py
planck_2020_lollipop/tests/test_lollipop.py
planck_2020_lollipop-4.1.1.dist-info/LICENSE
planck_2020_lollipop-4.1.1.dist-info/METADATA
planck_2020_lollipop-4.1.1.dist-info/WHEEL
planck_2020_lollipop-4.1.1.dist-info/top_level.txt
planck_2020_lollipop-4.1.1.dist-info/RECORD
