Metadata-Version: 2.1
Name: planck_2020_lollipop
Version: 4.1.1
Summary: A cobaya low-ell likelihood polarized for planck
Author: Matthieu Tristram
License: GNU GENERAL PUBLIC LICENSE
Project-URL: Homepage, https://github.com/planck-npipe/lollipop
Project-URL: Documentation, https://github.com/planck-npipe/lollipop
Project-URL: Source, https://github.com/planck-npipe/lollipop
Project-URL: Tracker, https://github.com/planck-npipe/lollipop/issues
Project-URL: Licensing, https://github.com/planck-npipe/lollipop/blob/master/LICENCE
Classifier: Intended Audience :: Developers
Classifier: License :: OSI Approved :: GNU General Public License v3 (GPLv3)
Classifier: Natural Language :: English
Classifier: Programming Language :: Python :: 3.8
Classifier: Programming Language :: Python :: 3.9
Classifier: Programming Language :: Python :: 3.10
Requires-Python: >=3.8.0
License-File: LICENSE
Requires-Dist: astropy
Requires-Dist: cobaya >=3.4
